Metadata-Version: 1.1
Name: tcs-sdk
Version: 1.3.2
Summary: Tensorflow as service  Python Sdk
Home-page: https://github.com/yowenter
Author: Wenter W
Author-email: wenter.wu@gmail.com
License: MIT License
Keywords: tensorflow sdk
Platform: UNKNOWN
Classifier: Programming Language :: Python :: 3.6
